MRUs/Eelementary_Row_Operations.py
MRUs/LU.py
MRUs/Orthogonal_Reduction.py
MRUs/QR.py
MRUs/URV.py
MRUs/__init__.py
MRUs-0.0.7.dist-info/METADATA
MRUs-0.0.7.dist-info/WHEEL
MRUs-0.0.7.dist-info/top_level.txt
MRUs-0.0.7.dist-info/RECORD
