Metadata-Version: 2.1
Name: MRUs
Version: 0.0.7
Summary: Matrix Reduction Utils
Author: MingjunXu
Requires: numpy
